implicit_word_network/__init__.py
implicit_word_network/build_graph.py
implicit_word_network/lib.py
implicit_word_network/parse_documents.py
implicit_word_network-0.0.1.dist-info/LICENSE
implicit_word_network-0.0.1.dist-info/METADATA
implicit_word_network-0.0.1.dist-info/WHEEL
implicit_word_network-0.0.1.dist-info/top_level.txt
implicit_word_network-0.0.1.dist-info/RECORD
