Metadata-Version: 2.1
Name: implicit-word-network
Version: 0.0.1
Summary: A python package for extracting and exploring context-enriched word networks from corpora
Home-page: https://gitlab.inf.uni-konstanz.de/julian.schelb/implicit-word-network
Author: Julian Schelb
Author-email: julian.schelb@uni-konstanz.de
License: UNKNOWN
Project-URL: Bug Tracker, https://gitlab.inf.uni-konstanz.de/julian.schelb/implicit-word-network/-/issues
Platform: UNKNOWN
Classifier: Development Status :: 3 - Alpha
Classifier: Programming Language :: Python :: 3
Classifier: License :: OSI Approved :: MIT License
Classifier: Operating System :: OS Independent
Requires-Python: >=3.6
License-File: LICENSE
Requires-Dist: sklearn
Requires-Dist: tqdm
